{"nodes": [{"id": "src_modules_image_image_blur_js", "label": "image.blur.js", "file_type": "code", "source_file": "src/modules/image/image.blur.js", "source_location": "L1"}, {"id": "image_blur_islocaluploadpath", "label": "isLocalUploadPath()", "file_type": "code", "source_file": "src/modules/image/image.blur.js", "source_location": "L17"}, {"id": "image_blur_blurimageforllm", "label": "blurImageForLLM()", "file_type": "code", "source_file": "src/modules/image/image.blur.js", "source_location": "L31"}], "edges": [{"source": "src_modules_image_image_blur_js", "target": "path", "relation": "imports_from", "confidence": "EXTRACTED", "source_file": "src/modules/image/image.blur.js", "source_location": "L1", "weight": 1.0}, {"source": "src_modules_image_image_blur_js", "target": "url", "relation": "imports_from", "confidence": "EXTRACTED", "source_file": "src/modules/image/image.blur.js", "source_location": "L2", "weight": 1.0}, {"source": "src_modules_image_image_blur_js", "target": "sharp", "relation": "imports_from", "confidence": "EXTRACTED", "source_file": "src/modules/image/image.blur.js", "source_location": "L3", "weight": 1.0}, {"source": "src_modules_image_image_blur_js", "target": "image_blur_islocaluploadpath", "relation": "contains", "confidence": "EXTRACTED", "source_file": "src/modules/image/image.blur.js", "source_location": "L17", "weight": 1.0}, {"source": "src_modules_image_image_blur_js", "target": "image_blur_blurimageforllm", "relation": "contains", "confidence": "EXTRACTED", "source_file": "src/modules/image/image.blur.js", "source_location": "L31", "weight": 1.0}], "raw_calls": [{"caller_nid": "image_blur_islocaluploadpath", "callee": "startsWith", "source_file": "src/modules/image/image.blur.js", "source_location": "L18"}, {"caller_nid": "image_blur_blurimageforllm", "callee": "join", "source_file": "src/modules/image/image.blur.js", "source_location": "L32"}, {"caller_nid": "image_blur_blurimageforllm", "callee": "sharp", "source_file": "src/modules/image/image.blur.js", "source_location": "L34"}, {"caller_nid": "image_blur_blurimageforllm", "callee": "blur", "source_file": "src/modules/image/image.blur.js", "source_location": "L38"}, {"caller_nid": "image_blur_blurimageforllm", "callee": "toBuffer", "source_file": "src/modules/image/image.blur.js", "source_location": "L41"}, {"caller_nid": "image_blur_blurimageforllm", "callee": "toString", "source_file": "src/modules/image/image.blur.js", "source_location": "L43"}]}